{
  "competidor": {
    "id": "cmrkslam500gdrde8tyf4qsis",
    "nombre": "BAMIDAL S.A.",
    "cuit": null,
    "pais": null,
    "activo": true
  },
  "operaciones": [
    {
      "id": "cmrksm16p1a6orde8k5kb7sq1",
      "productorId": "cmrkslac50096rde8wb5mshvg",
      "certificadorId": null,
      "competidorId": "cmrkslam500gdrde8tyf4qsis",
      "destinoId": "cmrksl9zf000arde84pjk649e",
      "contenedorId": null,
      "importacionId": "cmrksl9z60003rde8f5zrkgr1",
      "fecha": "2025-12-04T11:28:00.000Z",
      "periodo": "2025-12",
      "producto": "CARNE OVINA CON HUESO CONGELADA",
      "cantidad": 1521,
      "pesoKg": 18816,
      "valorUsd": 0,
      "createdAt": "2026-07-14T15:15:13.907Z",
      "updatedAt": "2026-07-14T15:15:13.907Z",
      "productor": {
        "id": "cmrkslac50096rde8wb5mshvg",
        "nombre": "BAMIDAL S.A.",
        "cuit": null,
        "razonSocial": null,
        "pais": "Uruguay",
        "provincia": null,
        "localidad": null,
        "activo": true,
        "createdAt": "2026-07-14T15:14:39.126Z",
        "updatedAt": "2026-07-14T15:14:39.126Z"
      },
      "destino": {
        "id": "cmrksl9zf000arde84pjk649e",
        "nombre": "BRASIL",
        "pais": "BRASIL",
        "region": null,
        "createdAt": "2026-07-14T15:14:38.667Z",
        "updatedAt": "2026-07-14T15:14:38.667Z"
      }
    },
    {
      "id": "cmrksm16i19rerde8qaxqu9xy",
      "productorId": "cmrkslac50096rde8wb5mshvg",
      "certificadorId": null,
      "competidorId": "cmrkslam500gdrde8tyf4qsis",
      "destinoId": "cmrksl9z90006rde8v9spkh5v",
      "contenedorId": null,
      "importacionId": "cmrksl9z60003rde8f5zrkgr1",
      "fecha": "2025-11-29T12:49:59.999Z",
      "periodo": "2025-11",
      "producto": "TRIPAS OVINAS",
      "cantidad": 326,
      "pesoKg": 6520,
      "valorUsd": 0,
      "createdAt": "2026-07-14T15:15:13.907Z",
      "updatedAt": "2026-07-14T15:15:13.907Z",
      "productor": {
        "id": "cmrkslac50096rde8wb5mshvg",
        "nombre": "BAMIDAL S.A.",
        "cuit": null,
        "razonSocial": null,
        "pais": "Uruguay",
        "provincia": null,
        "localidad": null,
        "activo": true,
        "createdAt": "2026-07-14T15:14:39.126Z",
        "updatedAt": "2026-07-14T15:14:39.126Z"
      },
      "destino": {
        "id": "cmrksl9z90006rde8v9spkh5v",
        "nombre": "TERCEROS PAISES SÓLO A DEPÓSITOS",
        "pais": "TERCEROS PAISES SÓLO A DEPÓSITOS",
        "region": null,
        "createdAt": "2026-07-14T15:14:38.662Z",
        "updatedAt": "2026-07-14T15:14:38.662Z"
      }
    },
    {
      "id": "cmrksm0gv18o4rde8wquq68id",
      "productorId": "cmrkslac50096rde8wb5mshvg",
      "certificadorId": null,
      "competidorId": "cmrkslam500gdrde8tyf4qsis",
      "destinoId": "cmrksl9zf000arde84pjk649e",
      "contenedorId": null,
      "importacionId": "cmrksl9z60003rde8f5zrkgr1",
      "fecha": "2025-11-24T15:36:59.999Z",
      "periodo": "2025-11",
      "producto": "CARNE OVINA CON HUESO CONGELADA",
      "cantidad": 1720,
      "pesoKg": 19846,
      "valorUsd": 0,
      "createdAt": "2026-07-14T15:15:12.982Z",
      "updatedAt": "2026-07-14T15:15:12.982Z",
      "productor": {
        "id": "cmrkslac50096rde8wb5mshvg",
        "nombre": "BAMIDAL S.A.",
        "cuit": null,
        "razonSocial": null,
        "pais": "Uruguay",
        "provincia": null,
        "localidad": null,
        "activo": true,
        "createdAt": "2026-07-14T15:14:39.126Z",
        "updatedAt": "2026-07-14T15:14:39.126Z"
      },
      "destino": {
        "id": "cmrksl9zf000arde84pjk649e",
        "nombre": "BRASIL",
        "pais": "BRASIL",
        "region": null,
        "createdAt": "2026-07-14T15:14:38.667Z",
        "updatedAt": "2026-07-14T15:14:38.667Z"
      }
    },
    {
      "id": "cmrksm0gu18myrde8liyues8h",
      "productorId": "cmrkslac50096rde8wb5mshvg",
      "certificadorId": null,
      "competidorId": "cmrkslam500gdrde8tyf4qsis",
      "destinoId": "cmrksl9zf000arde84pjk649e",
      "contenedorId": null,
      "importacionId": "cmrksl9z60003rde8f5zrkgr1",
      "fecha": "2025-11-24T13:07:00.000Z",
      "periodo": "2025-11",
      "producto": "CARNE OVINA CON HUESO CONGELADA",
      "cantidad": 609,
      "pesoKg": 11258,
      "valorUsd": 0,
      "createdAt": "2026-07-14T15:15:12.982Z",
      "updatedAt": "2026-07-14T15:15:12.982Z",
      "productor": {
        "id": "cmrkslac50096rde8wb5mshvg",
        "nombre": "BAMIDAL S.A.",
        "cuit": null,
        "razonSocial": null,
        "pais": "Uruguay",
        "provincia": null,
        "localidad": null,
        "activo": true,
        "createdAt": "2026-07-14T15:14:39.126Z",
        "updatedAt": "2026-07-14T15:14:39.126Z"
      },
      "destino": {
        "id": "cmrksl9zf000arde84pjk649e",
        "nombre": "BRASIL",
        "pais": "BRASIL",
        "region": null,
        "createdAt": "2026-07-14T15:14:38.667Z",
        "updatedAt": "2026-07-14T15:14:38.667Z"
      }
    },
    {
      "id": "cmrksm0gu18n1rde8afo9olc6",
      "productorId": "cmrkslac50096rde8wb5mshvg",
      "certificadorId": null,
      "competidorId": "cmrkslam500gdrde8tyf4qsis",
      "destinoId": "cmrksl9z90006rde8v9spkh5v",
      "contenedorId": null,
      "importacionId": "cmrksl9z60003rde8f5zrkgr1",
      "fecha": "2025-11-24T13:07:00.000Z",
      "periodo": "2025-11",
      "producto": "CARNE OVINA SIN HUESO CONGELADA",
      "cantidad": 47,
      "pesoKg": 881,
      "valorUsd": 0,
      "createdAt": "2026-07-14T15:15:12.982Z",
      "updatedAt": "2026-07-14T15:15:12.982Z",
      "productor": {
        "id": "cmrkslac50096rde8wb5mshvg",
        "nombre": "BAMIDAL S.A.",
        "cuit": null,
        "razonSocial": null,
        "pais": "Uruguay",
        "provincia": null,
        "localidad": null,
        "activo": true,
        "createdAt": "2026-07-14T15:14:39.126Z",
        "updatedAt": "2026-07-14T15:14:39.126Z"
      },
      "destino": {
        "id": "cmrksl9z90006rde8v9spkh5v",
        "nombre": "TERCEROS PAISES SÓLO A DEPÓSITOS",
        "pais": "TERCEROS PAISES SÓLO A DEPÓSITOS",
        "region": null,
        "createdAt": "2026-07-14T15:14:38.662Z",
        "updatedAt": "2026-07-14T15:14:38.662Z"
      }
    },
    {
      "id": "cmrksm0gu18n4rde8eve9u0wi",
      "productorId": "cmrkslac50096rde8wb5mshvg",
      "certificadorId": null,
      "competidorId": "cmrkslam500gdrde8tyf4qsis",
      "destinoId": "cmrksla5q0040rde81mdgkryj",
      "contenedorId": null,
      "importacionId": "cmrksl9z60003rde8f5zrkgr1",
      "fecha": "2025-11-24T13:07:00.000Z",
      "periodo": "2025-11",
      "producto": "SUBPRODUCTO OVINO NO COMESTIBLE",
      "cantidad": 101,
      "pesoKg": 1615,
      "valorUsd": 0,
      "createdAt": "2026-07-14T15:15:12.982Z",
      "updatedAt": "2026-07-14T15:15:12.982Z",
      "productor": {
        "id": "cmrkslac50096rde8wb5mshvg",
        "nombre": "BAMIDAL S.A.",
        "cuit": null,
        "razonSocial": null,
        "pais": "Uruguay",
        "provincia": null,
        "localidad": null,
        "activo": true,
        "createdAt": "2026-07-14T15:14:39.126Z",
        "updatedAt": "2026-07-14T15:14:39.126Z"
      },
      "destino": {
        "id": "cmrksla5q0040rde81mdgkryj",
        "nombre": "UNION EUROPEA SÓLO A DEPÓSITO",
        "pais": "UNION EUROPEA SÓLO A DEPÓSITO",
        "region": null,
        "createdAt": "2026-07-14T15:14:38.894Z",
        "updatedAt": "2026-07-14T15:14:38.894Z"
      }
    },
    {
      "id": "cmrkslzqs17bmrde89gcc5clu",
      "productorId": "cmrkslac50096rde8wb5mshvg",
      "certificadorId": null,
      "competidorId": "cmrkslam500gdrde8tyf4qsis",
      "destinoId": "cmrksl9zf000arde84pjk649e",
      "contenedorId": null,
      "importacionId": "cmrksl9z60003rde8f5zrkgr1",
      "fecha": "2025-11-14T14:17:00.000Z",
      "periodo": "2025-11",
      "producto": "CARNE OVINA CON HUESOS EN CORTES",
      "cantidad": 828,
      "pesoKg": 9196,
      "valorUsd": 0,
      "createdAt": "2026-07-14T15:15:12.045Z",
      "updatedAt": "2026-07-14T15:15:12.045Z",
      "productor": {
        "id": "cmrkslac50096rde8wb5mshvg",
        "nombre": "BAMIDAL S.A.",
        "cuit": null,
        "razonSocial": null,
        "pais": "Uruguay",
        "provincia": null,
        "localidad": null,
        "activo": true,
        "createdAt": "2026-07-14T15:14:39.126Z",
        "updatedAt": "2026-07-14T15:14:39.126Z"
      },
      "destino": {
        "id": "cmrksl9zf000arde84pjk649e",
        "nombre": "BRASIL",
        "pais": "BRASIL",
        "region": null,
        "createdAt": "2026-07-14T15:14:38.667Z",
        "updatedAt": "2026-07-14T15:14:38.667Z"
      }
    },
    {
      "id": "cmrkslzqs17cmrde80ha2ssq6",
      "productorId": "cmrkslac50096rde8wb5mshvg",
      "certificadorId": null,
      "competidorId": "cmrkslam500gdrde8tyf4qsis",
      "destinoId": "cmrksl9z90006rde8v9spkh5v",
      "contenedorId": null,
      "importacionId": "cmrksl9z60003rde8f5zrkgr1",
      "fecha": "2025-11-14T14:17:00.000Z",
      "periodo": "2025-11",
      "producto": "CARNE OVINA SIN HUESO ENFRIADA",
      "cantidad": 14,
      "pesoKg": 263,
      "valorUsd": 0,
      "createdAt": "2026-07-14T15:15:12.045Z",
      "updatedAt": "2026-07-14T15:15:12.045Z",
      "productor": {
        "id": "cmrkslac50096rde8wb5mshvg",
        "nombre": "BAMIDAL S.A.",
        "cuit": null,
        "razonSocial": null,
        "pais": "Uruguay",
        "provincia": null,
        "localidad": null,
        "activo": true,
        "createdAt": "2026-07-14T15:14:39.126Z",
        "updatedAt": "2026-07-14T15:14:39.126Z"
      },
      "destino": {
        "id": "cmrksl9z90006rde8v9spkh5v",
        "nombre": "TERCEROS PAISES SÓLO A DEPÓSITOS",
        "pais": "TERCEROS PAISES SÓLO A DEPÓSITOS",
        "region": null,
        "createdAt": "2026-07-14T15:14:38.662Z",
        "updatedAt": "2026-07-14T15:14:38.662Z"
      }
    },
    {
      "id": "cmrkslzqs17berde8d7w656xv",
      "productorId": "cmrkslac50096rde8wb5mshvg",
      "certificadorId": null,
      "competidorId": "cmrkslam500gdrde8tyf4qsis",
      "destinoId": "cmrksl9zf000arde84pjk649e",
      "contenedorId": null,
      "importacionId": "cmrksl9z60003rde8f5zrkgr1",
      "fecha": "2025-11-14T12:08:00.000Z",
      "periodo": "2025-11",
      "producto": "CARNE OVINA CON HUESO CONGELADA",
      "cantidad": 281,
      "pesoKg": 3325,
      "valorUsd": 0,
      "createdAt": "2026-07-14T15:15:12.045Z",
      "updatedAt": "2026-07-14T15:15:12.045Z",
      "productor": {
        "id": "cmrkslac50096rde8wb5mshvg",
        "nombre": "BAMIDAL S.A.",
        "cuit": null,
        "razonSocial": null,
        "pais": "Uruguay",
        "provincia": null,
        "localidad": null,
        "activo": true,
        "createdAt": "2026-07-14T15:14:39.126Z",
        "updatedAt": "2026-07-14T15:14:39.126Z"
      },
      "destino": {
        "id": "cmrksl9zf000arde84pjk649e",
        "nombre": "BRASIL",
        "pais": "BRASIL",
        "region": null,
        "createdAt": "2026-07-14T15:14:38.667Z",
        "updatedAt": "2026-07-14T15:14:38.667Z"
      }
    },
    {
      "id": "cmrkslzqs17bprde8wasw34o0",
      "productorId": "cmrkslac50096rde8wb5mshvg",
      "certificadorId": null,
      "competidorId": "cmrkslam500gdrde8tyf4qsis",
      "destinoId": "cmrksl9z90006rde8v9spkh5v",
      "contenedorId": null,
      "importacionId": "cmrksl9z60003rde8f5zrkgr1",
      "fecha": "2025-11-14T12:08:00.000Z",
      "periodo": "2025-11",
      "producto": "CARNE OVINA SIN HUESO CONGELADA",
      "cantidad": 38,
      "pesoKg": 725,
      "valorUsd": 0,
      "createdAt": "2026-07-14T15:15:12.045Z",
      "updatedAt": "2026-07-14T15:15:12.045Z",
      "productor": {
        "id": "cmrkslac50096rde8wb5mshvg",
        "nombre": "BAMIDAL S.A.",
        "cuit": null,
        "razonSocial": null,
        "pais": "Uruguay",
        "provincia": null,
        "localidad": null,
        "activo": true,
        "createdAt": "2026-07-14T15:14:39.126Z",
        "updatedAt": "2026-07-14T15:14:39.126Z"
      },
      "destino": {
        "id": "cmrksl9z90006rde8v9spkh5v",
        "nombre": "TERCEROS PAISES SÓLO A DEPÓSITOS",
        "pais": "TERCEROS PAISES SÓLO A DEPÓSITOS",
        "region": null,
        "createdAt": "2026-07-14T15:14:38.662Z",
        "updatedAt": "2026-07-14T15:14:38.662Z"
      }
    },
    {
      "id": "cmrkslyy716mdrde823ts0nnq",
      "productorId": "cmrkslac50096rde8wb5mshvg",
      "certificadorId": null,
      "competidorId": "cmrkslam500gdrde8tyf4qsis",
      "destinoId": "cmrksl9zf000arde84pjk649e",
      "contenedorId": null,
      "importacionId": "cmrksl9z60003rde8f5zrkgr1",
      "fecha": "2025-11-12T11:46:00.000Z",
      "periodo": "2025-11",
      "producto": "CARNE OVINA CON HUESO CONGELADA",
      "cantidad": 1299,
      "pesoKg": 21494,
      "valorUsd": 0,
      "createdAt": "2026-07-14T15:15:11.008Z",
      "updatedAt": "2026-07-14T15:15:11.008Z",
      "productor": {
        "id": "cmrkslac50096rde8wb5mshvg",
        "nombre": "BAMIDAL S.A.",
        "cuit": null,
        "razonSocial": null,
        "pais": "Uruguay",
        "provincia": null,
        "localidad": null,
        "activo": true,
        "createdAt": "2026-07-14T15:14:39.126Z",
        "updatedAt": "2026-07-14T15:14:39.126Z"
      },
      "destino": {
        "id": "cmrksl9zf000arde84pjk649e",
        "nombre": "BRASIL",
        "pais": "BRASIL",
        "region": null,
        "createdAt": "2026-07-14T15:14:38.667Z",
        "updatedAt": "2026-07-14T15:14:38.667Z"
      }
    },
    {
      "id": "cmrkslyy316dorde86m1cwfmc",
      "productorId": "cmrkslac50096rde8wb5mshvg",
      "certificadorId": null,
      "competidorId": "cmrkslam500gdrde8tyf4qsis",
      "destinoId": "cmrksl9zf000arde84pjk649e",
      "contenedorId": null,
      "importacionId": "cmrksl9z60003rde8f5zrkgr1",
      "fecha": "2025-11-12T09:04:59.999Z",
      "periodo": "2025-11",
      "producto": "CARNE OVINA CON HUESOS EN CORTES",
      "cantidad": 1046,
      "pesoKg": 14895,
      "valorUsd": 0,
      "createdAt": "2026-07-14T15:15:11.008Z",
      "updatedAt": "2026-07-14T15:15:11.008Z",
      "productor": {
        "id": "cmrkslac50096rde8wb5mshvg",
        "nombre": "BAMIDAL S.A.",
        "cuit": null,
        "razonSocial": null,
        "pais": "Uruguay",
        "provincia": null,
        "localidad": null,
        "activo": true,
        "createdAt": "2026-07-14T15:14:39.126Z",
        "updatedAt": "2026-07-14T15:14:39.126Z"
      },
      "destino": {
        "id": "cmrksl9zf000arde84pjk649e",
        "nombre": "BRASIL",
        "pais": "BRASIL",
        "region": null,
        "createdAt": "2026-07-14T15:14:38.667Z",
        "updatedAt": "2026-07-14T15:14:38.667Z"
      }
    },
    {
      "id": "cmrkslyy316d4rde8v6wed0br",
      "productorId": "cmrkslac50096rde8wb5mshvg",
      "certificadorId": null,
      "competidorId": "cmrkslam500gdrde8tyf4qsis",
      "destinoId": "cmrksla5q0040rde81mdgkryj",
      "contenedorId": null,
      "importacionId": "cmrksl9z60003rde8f5zrkgr1",
      "fecha": "2025-11-12T08:06:00.000Z",
      "periodo": "2025-11",
      "producto": "SUBPRODUCTO OVINO NO COMESTIBLE",
      "cantidad": 43,
      "pesoKg": 708,
      "valorUsd": 0,
      "createdAt": "2026-07-14T15:15:11.008Z",
      "updatedAt": "2026-07-14T15:15:11.008Z",
      "productor": {
        "id": "cmrkslac50096rde8wb5mshvg",
        "nombre": "BAMIDAL S.A.",
        "cuit": null,
        "razonSocial": null,
        "pais": "Uruguay",
        "provincia": null,
        "localidad": null,
        "activo": true,
        "createdAt": "2026-07-14T15:14:39.126Z",
        "updatedAt": "2026-07-14T15:14:39.126Z"
      },
      "destino": {
        "id": "cmrksla5q0040rde81mdgkryj",
        "nombre": "UNION EUROPEA SÓLO A DEPÓSITO",
        "pais": "UNION EUROPEA SÓLO A DEPÓSITO",
        "region": null,
        "createdAt": "2026-07-14T15:14:38.894Z",
        "updatedAt": "2026-07-14T15:14:38.894Z"
      }
    },
    {
      "id": "cmrkslyy316darde8v3onrf27",
      "productorId": "cmrkslac50096rde8wb5mshvg",
      "certificadorId": null,
      "competidorId": "cmrkslam500gdrde8tyf4qsis",
      "destinoId": "cmrksl9zf000arde84pjk649e",
      "contenedorId": null,
      "importacionId": "cmrksl9z60003rde8f5zrkgr1",
      "fecha": "2025-11-12T08:06:00.000Z",
      "periodo": "2025-11",
      "producto": "CARNE OVINA CON HUESO CONGELADA",
      "cantidad": 177,
      "pesoKg": 1992,
      "valorUsd": 0,
      "createdAt": "2026-07-14T15:15:11.008Z",
      "updatedAt": "2026-07-14T15:15:11.008Z",
      "productor": {
        "id": "cmrkslac50096rde8wb5mshvg",
        "nombre": "BAMIDAL S.A.",
        "cuit": null,
        "razonSocial": null,
        "pais": "Uruguay",
        "provincia": null,
        "localidad": null,
        "activo": true,
        "createdAt": "2026-07-14T15:14:39.126Z",
        "updatedAt": "2026-07-14T15:14:39.126Z"
      },
      "destino": {
        "id": "cmrksl9zf000arde84pjk649e",
        "nombre": "BRASIL",
        "pais": "BRASIL",
        "region": null,
        "createdAt": "2026-07-14T15:14:38.667Z",
        "updatedAt": "2026-07-14T15:14:38.667Z"
      }
    },
    {
      "id": "cmrksluuc0zw1rde8t9vwk0uk",
      "productorId": "cmrkslac50096rde8wb5mshvg",
      "certificadorId": null,
      "competidorId": "cmrkslam500gdrde8tyf4qsis",
      "destinoId": "cmrksl9zf000arde84pjk649e",
      "contenedorId": null,
      "importacionId": "cmrksl9z60003rde8f5zrkgr1",
      "fecha": "2025-09-24T09:36:00.000Z",
      "periodo": "2025-09",
      "producto": "CARNE OVINA CON HUESO CONGELADA",
      "cantidad": 1117,
      "pesoKg": 20874,
      "valorUsd": 0,
      "createdAt": "2026-07-14T15:15:05.683Z",
      "updatedAt": "2026-07-14T15:15:05.683Z",
      "productor": {
        "id": "cmrkslac50096rde8wb5mshvg",
        "nombre": "BAMIDAL S.A.",
        "cuit": null,
        "razonSocial": null,
        "pais": "Uruguay",
        "provincia": null,
        "localidad": null,
        "activo": true,
        "createdAt": "2026-07-14T15:14:39.126Z",
        "updatedAt": "2026-07-14T15:14:39.126Z"
      },
      "destino": {
        "id": "cmrksl9zf000arde84pjk649e",
        "nombre": "BRASIL",
        "pais": "BRASIL",
        "region": null,
        "createdAt": "2026-07-14T15:14:38.667Z",
        "updatedAt": "2026-07-14T15:14:38.667Z"
      }
    },
    {
      "id": "cmrksluua0zrdrde803cp74gu",
      "productorId": "cmrkslac50096rde8wb5mshvg",
      "certificadorId": null,
      "competidorId": "cmrkslam500gdrde8tyf4qsis",
      "destinoId": "cmrksl9zf000arde84pjk649e",
      "contenedorId": null,
      "importacionId": "cmrksl9z60003rde8f5zrkgr1",
      "fecha": "2025-09-22T13:39:00.000Z",
      "periodo": "2025-09",
      "producto": "CARNE OVINA CON HUESOS EN CORTES",
      "cantidad": 856,
      "pesoKg": 14556,
      "valorUsd": 0,
      "createdAt": "2026-07-14T15:15:05.683Z",
      "updatedAt": "2026-07-14T15:15:05.683Z",
      "productor": {
        "id": "cmrkslac50096rde8wb5mshvg",
        "nombre": "BAMIDAL S.A.",
        "cuit": null,
        "razonSocial": null,
        "pais": "Uruguay",
        "provincia": null,
        "localidad": null,
        "activo": true,
        "createdAt": "2026-07-14T15:14:39.126Z",
        "updatedAt": "2026-07-14T15:14:39.126Z"
      },
      "destino": {
        "id": "cmrksl9zf000arde84pjk649e",
        "nombre": "BRASIL",
        "pais": "BRASIL",
        "region": null,
        "createdAt": "2026-07-14T15:14:38.667Z",
        "updatedAt": "2026-07-14T15:14:38.667Z"
      }
    },
    {
      "id": "cmrksluua0zrhrde8vcdm5wuq",
      "productorId": "cmrkslac50096rde8wb5mshvg",
      "certificadorId": null,
      "competidorId": "cmrkslam500gdrde8tyf4qsis",
      "destinoId": "cmrksl9z90006rde8v9spkh5v",
      "contenedorId": null,
      "importacionId": "cmrksl9z60003rde8f5zrkgr1",
      "fecha": "2025-09-22T13:39:00.000Z",
      "periodo": "2025-09",
      "producto": "CARNE OVINA SIN HUESO ENFRIADA",
      "cantidad": 11,
      "pesoKg": 204,
      "valorUsd": 0,
      "createdAt": "2026-07-14T15:15:05.683Z",
      "updatedAt": "2026-07-14T15:15:05.683Z",
      "productor": {
        "id": "cmrkslac50096rde8wb5mshvg",
        "nombre": "BAMIDAL S.A.",
        "cuit": null,
        "razonSocial": null,
        "pais": "Uruguay",
        "provincia": null,
        "localidad": null,
        "activo": true,
        "createdAt": "2026-07-14T15:14:39.126Z",
        "updatedAt": "2026-07-14T15:14:39.126Z"
      },
      "destino": {
        "id": "cmrksl9z90006rde8v9spkh5v",
        "nombre": "TERCEROS PAISES SÓLO A DEPÓSITOS",
        "pais": "TERCEROS PAISES SÓLO A DEPÓSITOS",
        "region": null,
        "createdAt": "2026-07-14T15:14:38.662Z",
        "updatedAt": "2026-07-14T15:14:38.662Z"
      }
    },
    {
      "id": "cmrksluua0zs6rde8krr5bmuy",
      "productorId": "cmrkslac50096rde8wb5mshvg",
      "certificadorId": null,
      "competidorId": "cmrkslam500gdrde8tyf4qsis",
      "destinoId": "cmrksla5q0040rde81mdgkryj",
      "contenedorId": null,
      "importacionId": "cmrksl9z60003rde8f5zrkgr1",
      "fecha": "2025-09-22T13:39:00.000Z",
      "periodo": "2025-09",
      "producto": "SUBPRODUCTO OVINO NO COMESTIBLE",
      "cantidad": 40,
      "pesoKg": 812,
      "valorUsd": 0,
      "createdAt": "2026-07-14T15:15:05.683Z",
      "updatedAt": "2026-07-14T15:15:05.683Z",
      "productor": {
        "id": "cmrkslac50096rde8wb5mshvg",
        "nombre": "BAMIDAL S.A.",
        "cuit": null,
        "razonSocial": null,
        "pais": "Uruguay",
        "provincia": null,
        "localidad": null,
        "activo": true,
        "createdAt": "2026-07-14T15:14:39.126Z",
        "updatedAt": "2026-07-14T15:14:39.126Z"
      },
      "destino": {
        "id": "cmrksla5q0040rde81mdgkryj",
        "nombre": "UNION EUROPEA SÓLO A DEPÓSITO",
        "pais": "UNION EUROPEA SÓLO A DEPÓSITO",
        "region": null,
        "createdAt": "2026-07-14T15:14:38.894Z",
        "updatedAt": "2026-07-14T15:14:38.894Z"
      }
    },
    {
      "id": "cmrksluua0zrarde8ebd3o07a",
      "productorId": "cmrkslac50096rde8wb5mshvg",
      "certificadorId": null,
      "competidorId": "cmrkslam500gdrde8tyf4qsis",
      "destinoId": "cmrksl9zf000arde84pjk649e",
      "contenedorId": null,
      "importacionId": "cmrksl9z60003rde8f5zrkgr1",
      "fecha": "2025-09-22T11:21:59.999Z",
      "periodo": "2025-09",
      "producto": "CARNE OVINA CON HUESO CONGELADA",
      "cantidad": 1,
      "pesoKg": 19,
      "valorUsd": 0,
      "createdAt": "2026-07-14T15:15:05.683Z",
      "updatedAt": "2026-07-14T15:15:05.683Z",
      "productor": {
        "id": "cmrkslac50096rde8wb5mshvg",
        "nombre": "BAMIDAL S.A.",
        "cuit": null,
        "razonSocial": null,
        "pais": "Uruguay",
        "provincia": null,
        "localidad": null,
        "activo": true,
        "createdAt": "2026-07-14T15:14:39.126Z",
        "updatedAt": "2026-07-14T15:14:39.126Z"
      },
      "destino": {
        "id": "cmrksl9zf000arde84pjk649e",
        "nombre": "BRASIL",
        "pais": "BRASIL",
        "region": null,
        "createdAt": "2026-07-14T15:14:38.667Z",
        "updatedAt": "2026-07-14T15:14:38.667Z"
      }
    },
    {
      "id": "cmrksluua0zrirde8i8t3vszp",
      "productorId": "cmrkslac50096rde8wb5mshvg",
      "certificadorId": null,
      "competidorId": "cmrkslam500gdrde8tyf4qsis",
      "destinoId": "cmrksla5q0040rde81mdgkryj",
      "contenedorId": null,
      "importacionId": "cmrksl9z60003rde8f5zrkgr1",
      "fecha": "2025-09-22T11:21:59.999Z",
      "periodo": "2025-09",
      "producto": "SUBPRODUCTO OVINO NO COMESTIBLE",
      "cantidad": 36,
      "pesoKg": 710,
      "valorUsd": 0,
      "createdAt": "2026-07-14T15:15:05.683Z",
      "updatedAt": "2026-07-14T15:15:05.683Z",
      "productor": {
        "id": "cmrkslac50096rde8wb5mshvg",
        "nombre": "BAMIDAL S.A.",
        "cuit": null,
        "razonSocial": null,
        "pais": "Uruguay",
        "provincia": null,
        "localidad": null,
        "activo": true,
        "createdAt": "2026-07-14T15:14:39.126Z",
        "updatedAt": "2026-07-14T15:14:39.126Z"
      },
      "destino": {
        "id": "cmrksla5q0040rde81mdgkryj",
        "nombre": "UNION EUROPEA SÓLO A DEPÓSITO",
        "pais": "UNION EUROPEA SÓLO A DEPÓSITO",
        "region": null,
        "createdAt": "2026-07-14T15:14:38.894Z",
        "updatedAt": "2026-07-14T15:14:38.894Z"
      }
    },
    {
      "id": "cmrksluu20z94rde865rwaikb",
      "productorId": "cmrkslac50096rde8wb5mshvg",
      "certificadorId": null,
      "competidorId": "cmrkslam500gdrde8tyf4qsis",
      "destinoId": "cmrksl9zf000arde84pjk649e",
      "contenedorId": null,
      "importacionId": "cmrksl9z60003rde8f5zrkgr1",
      "fecha": "2025-09-16T14:53:59.999Z",
      "periodo": "2025-09",
      "producto": "CARNE OVINA CON HUESOS EN CORTES",
      "cantidad": 446,
      "pesoKg": 7575,
      "valorUsd": 0,
      "createdAt": "2026-07-14T15:15:05.683Z",
      "updatedAt": "2026-07-14T15:15:05.683Z",
      "productor": {
        "id": "cmrkslac50096rde8wb5mshvg",
        "nombre": "BAMIDAL S.A.",
        "cuit": null,
        "razonSocial": null,
        "pais": "Uruguay",
        "provincia": null,
        "localidad": null,
        "activo": true,
        "createdAt": "2026-07-14T15:14:39.126Z",
        "updatedAt": "2026-07-14T15:14:39.126Z"
      },
      "destino": {
        "id": "cmrksl9zf000arde84pjk649e",
        "nombre": "BRASIL",
        "pais": "BRASIL",
        "region": null,
        "createdAt": "2026-07-14T15:14:38.667Z",
        "updatedAt": "2026-07-14T15:14:38.667Z"
      }
    },
    {
      "id": "cmrksluu20za4rde8zlltyx2r",
      "productorId": "cmrkslac50096rde8wb5mshvg",
      "certificadorId": null,
      "competidorId": "cmrkslam500gdrde8tyf4qsis",
      "destinoId": "cmrksl9z90006rde8v9spkh5v",
      "contenedorId": null,
      "importacionId": "cmrksl9z60003rde8f5zrkgr1",
      "fecha": "2025-09-16T14:53:59.999Z",
      "periodo": "2025-09",
      "producto": "CARNE OVINA SIN HUESO ENFRIADA",
      "cantidad": 8,
      "pesoKg": 162,
      "valorUsd": 0,
      "createdAt": "2026-07-14T15:15:05.683Z",
      "updatedAt": "2026-07-14T15:15:05.683Z",
      "productor": {
        "id": "cmrkslac50096rde8wb5mshvg",
        "nombre": "BAMIDAL S.A.",
        "cuit": null,
        "razonSocial": null,
        "pais": "Uruguay",
        "provincia": null,
        "localidad": null,
        "activo": true,
        "createdAt": "2026-07-14T15:14:39.126Z",
        "updatedAt": "2026-07-14T15:14:39.126Z"
      },
      "destino": {
        "id": "cmrksl9z90006rde8v9spkh5v",
        "nombre": "TERCEROS PAISES SÓLO A DEPÓSITOS",
        "pais": "TERCEROS PAISES SÓLO A DEPÓSITOS",
        "region": null,
        "createdAt": "2026-07-14T15:14:38.662Z",
        "updatedAt": "2026-07-14T15:14:38.662Z"
      }
    },
    {
      "id": "cmrksluu20z92rde8jtia7gjc",
      "productorId": "cmrkslac50096rde8wb5mshvg",
      "certificadorId": null,
      "competidorId": "cmrkslam500gdrde8tyf4qsis",
      "destinoId": "cmrksl9zf000arde84pjk649e",
      "contenedorId": null,
      "importacionId": "cmrksl9z60003rde8f5zrkgr1",
      "fecha": "2025-09-16T11:01:00.000Z",
      "periodo": "2025-09",
      "producto": "CARNE OVINA CON HUESO CONGELADA",
      "cantidad": 108,
      "pesoKg": 2250,
      "valorUsd": 0,
      "createdAt": "2026-07-14T15:15:05.683Z",
      "updatedAt": "2026-07-14T15:15:05.683Z",
      "productor": {
        "id": "cmrkslac50096rde8wb5mshvg",
        "nombre": "BAMIDAL S.A.",
        "cuit": null,
        "razonSocial": null,
        "pais": "Uruguay",
        "provincia": null,
        "localidad": null,
        "activo": true,
        "createdAt": "2026-07-14T15:14:39.126Z",
        "updatedAt": "2026-07-14T15:14:39.126Z"
      },
      "destino": {
        "id": "cmrksl9zf000arde84pjk649e",
        "nombre": "BRASIL",
        "pais": "BRASIL",
        "region": null,
        "createdAt": "2026-07-14T15:14:38.667Z",
        "updatedAt": "2026-07-14T15:14:38.667Z"
      }
    },
    {
      "id": "cmrksluu20z96rde885wukgtf",
      "productorId": "cmrkslac50096rde8wb5mshvg",
      "certificadorId": null,
      "competidorId": "cmrkslam500gdrde8tyf4qsis",
      "destinoId": "cmrksla5q0040rde81mdgkryj",
      "contenedorId": null,
      "importacionId": "cmrksl9z60003rde8f5zrkgr1",
      "fecha": "2025-09-16T11:01:00.000Z",
      "periodo": "2025-09",
      "producto": "SUBPRODUCTO OVINO NO COMESTIBLE",
      "cantidad": 161,
      "pesoKg": 3009,
      "valorUsd": 0,
      "createdAt": "2026-07-14T15:15:05.683Z",
      "updatedAt": "2026-07-14T15:15:05.683Z",
      "productor": {
        "id": "cmrkslac50096rde8wb5mshvg",
        "nombre": "BAMIDAL S.A.",
        "cuit": null,
        "razonSocial": null,
        "pais": "Uruguay",
        "provincia": null,
        "localidad": null,
        "activo": true,
        "createdAt": "2026-07-14T15:14:39.126Z",
        "updatedAt": "2026-07-14T15:14:39.126Z"
      },
      "destino": {
        "id": "cmrksla5q0040rde81mdgkryj",
        "nombre": "UNION EUROPEA SÓLO A DEPÓSITO",
        "pais": "UNION EUROPEA SÓLO A DEPÓSITO",
        "region": null,
        "createdAt": "2026-07-14T15:14:38.894Z",
        "updatedAt": "2026-07-14T15:14:38.894Z"
      }
    },
    {
      "id": "cmrksluu20z99rde8azmwfyjo",
      "productorId": "cmrkslac50096rde8wb5mshvg",
      "certificadorId": null,
      "competidorId": "cmrkslam500gdrde8tyf4qsis",
      "destinoId": "cmrksl9z90006rde8v9spkh5v",
      "contenedorId": null,
      "importacionId": "cmrksl9z60003rde8f5zrkgr1",
      "fecha": "2025-09-16T11:01:00.000Z",
      "periodo": "2025-09",
      "producto": "CARNE OVINA SIN HUESO CONGELADA",
      "cantidad": 47,
      "pesoKg": 945,
      "valorUsd": 0,
      "createdAt": "2026-07-14T15:15:05.683Z",
      "updatedAt": "2026-07-14T15:15:05.683Z",
      "productor": {
        "id": "cmrkslac50096rde8wb5mshvg",
        "nombre": "BAMIDAL S.A.",
        "cuit": null,
        "razonSocial": null,
        "pais": "Uruguay",
        "provincia": null,
        "localidad": null,
        "activo": true,
        "createdAt": "2026-07-14T15:14:39.126Z",
        "updatedAt": "2026-07-14T15:14:39.126Z"
      },
      "destino": {
        "id": "cmrksl9z90006rde8v9spkh5v",
        "nombre": "TERCEROS PAISES SÓLO A DEPÓSITOS",
        "pais": "TERCEROS PAISES SÓLO A DEPÓSITOS",
        "region": null,
        "createdAt": "2026-07-14T15:14:38.662Z",
        "updatedAt": "2026-07-14T15:14:38.662Z"
      }
    },
    {
      "id": "cmrkslthg0x2brde85sq67mqt",
      "productorId": "cmrkslac50096rde8wb5mshvg",
      "certificadorId": null,
      "competidorId": "cmrkslam500gdrde8tyf4qsis",
      "destinoId": "cmrksl9zf000arde84pjk649e",
      "contenedorId": null,
      "importacionId": "cmrksl9z60003rde8f5zrkgr1",
      "fecha": "2025-09-01T14:55:00.000Z",
      "periodo": "2025-09",
      "producto": "CARNE OVINA CON HUESOS EN CORTES",
      "cantidad": 330,
      "pesoKg": 5151,
      "valorUsd": 0,
      "createdAt": "2026-07-14T15:15:03.933Z",
      "updatedAt": "2026-07-14T15:15:03.933Z",
      "productor": {
        "id": "cmrkslac50096rde8wb5mshvg",
        "nombre": "BAMIDAL S.A.",
        "cuit": null,
        "razonSocial": null,
        "pais": "Uruguay",
        "provincia": null,
        "localidad": null,
        "activo": true,
        "createdAt": "2026-07-14T15:14:39.126Z",
        "updatedAt": "2026-07-14T15:14:39.126Z"
      },
      "destino": {
        "id": "cmrksl9zf000arde84pjk649e",
        "nombre": "BRASIL",
        "pais": "BRASIL",
        "region": null,
        "createdAt": "2026-07-14T15:14:38.667Z",
        "updatedAt": "2026-07-14T15:14:38.667Z"
      }
    },
    {
      "id": "cmrkslthg0x2arde8zd2k7ec0",
      "productorId": "cmrkslac50096rde8wb5mshvg",
      "certificadorId": null,
      "competidorId": "cmrkslam500gdrde8tyf4qsis",
      "destinoId": "cmrksl9zf000arde84pjk649e",
      "contenedorId": null,
      "importacionId": "cmrksl9z60003rde8f5zrkgr1",
      "fecha": "2025-09-01T12:24:00.000Z",
      "periodo": "2025-09",
      "producto": "CARNE OVINA CON HUESO CONGELADA",
      "cantidad": 618,
      "pesoKg": 10080,
      "valorUsd": 0,
      "createdAt": "2026-07-14T15:15:03.933Z",
      "updatedAt": "2026-07-14T15:15:03.933Z",
      "productor": {
        "id": "cmrkslac50096rde8wb5mshvg",
        "nombre": "BAMIDAL S.A.",
        "cuit": null,
        "razonSocial": null,
        "pais": "Uruguay",
        "provincia": null,
        "localidad": null,
        "activo": true,
        "createdAt": "2026-07-14T15:14:39.126Z",
        "updatedAt": "2026-07-14T15:14:39.126Z"
      },
      "destino": {
        "id": "cmrksl9zf000arde84pjk649e",
        "nombre": "BRASIL",
        "pais": "BRASIL",
        "region": null,
        "createdAt": "2026-07-14T15:14:38.667Z",
        "updatedAt": "2026-07-14T15:14:38.667Z"
      }
    },
    {
      "id": "cmrkslthh0x2krde8ge7iwe7v",
      "productorId": "cmrkslac50096rde8wb5mshvg",
      "certificadorId": null,
      "competidorId": "cmrkslam500gdrde8tyf4qsis",
      "destinoId": "cmrksla5q0040rde81mdgkryj",
      "contenedorId": null,
      "importacionId": "cmrksl9z60003rde8f5zrkgr1",
      "fecha": "2025-09-01T12:24:00.000Z",
      "periodo": "2025-09",
      "producto": "SUBPRODUCTO OVINO NO COMESTIBLE",
      "cantidad": 117,
      "pesoKg": 2125,
      "valorUsd": 0,
      "createdAt": "2026-07-14T15:15:03.933Z",
      "updatedAt": "2026-07-14T15:15:03.933Z",
      "productor": {
        "id": "cmrkslac50096rde8wb5mshvg",
        "nombre": "BAMIDAL S.A.",
        "cuit": null,
        "razonSocial": null,
        "pais": "Uruguay",
        "provincia": null,
        "localidad": null,
        "activo": true,
        "createdAt": "2026-07-14T15:14:39.126Z",
        "updatedAt": "2026-07-14T15:14:39.126Z"
      },
      "destino": {
        "id": "cmrksla5q0040rde81mdgkryj",
        "nombre": "UNION EUROPEA SÓLO A DEPÓSITO",
        "pais": "UNION EUROPEA SÓLO A DEPÓSITO",
        "region": null,
        "createdAt": "2026-07-14T15:14:38.894Z",
        "updatedAt": "2026-07-14T15:14:38.894Z"
      }
    },
    {
      "id": "cmrkslthh0x3xrde8nzagd13z",
      "productorId": "cmrkslac50096rde8wb5mshvg",
      "certificadorId": null,
      "competidorId": "cmrkslam500gdrde8tyf4qsis",
      "destinoId": "cmrksl9z90006rde8v9spkh5v",
      "contenedorId": null,
      "importacionId": "cmrksl9z60003rde8f5zrkgr1",
      "fecha": "2025-09-01T12:24:00.000Z",
      "periodo": "2025-09",
      "producto": "CARNE OVINA SIN HUESO CONGELADA",
      "cantidad": 32,
      "pesoKg": 622,
      "valorUsd": 0,
      "createdAt": "2026-07-14T15:15:03.933Z",
      "updatedAt": "2026-07-14T15:15:03.933Z",
      "productor": {
        "id": "cmrkslac50096rde8wb5mshvg",
        "nombre": "BAMIDAL S.A.",
        "cuit": null,
        "razonSocial": null,
        "pais": "Uruguay",
        "provincia": null,
        "localidad": null,
        "activo": true,
        "createdAt": "2026-07-14T15:14:39.126Z",
        "updatedAt": "2026-07-14T15:14:39.126Z"
      },
      "destino": {
        "id": "cmrksl9z90006rde8v9spkh5v",
        "nombre": "TERCEROS PAISES SÓLO A DEPÓSITOS",
        "pais": "TERCEROS PAISES SÓLO A DEPÓSITOS",
        "region": null,
        "createdAt": "2026-07-14T15:14:38.662Z",
        "updatedAt": "2026-07-14T15:14:38.662Z"
      }
    },
    {
      "id": "cmrkslthe0wxurde837x8qzy9",
      "productorId": "cmrkslac50096rde8wb5mshvg",
      "certificadorId": null,
      "competidorId": "cmrkslam500gdrde8tyf4qsis",
      "destinoId": "cmrksl9z90006rde8v9spkh5v",
      "contenedorId": null,
      "importacionId": "cmrksl9z60003rde8f5zrkgr1",
      "fecha": "2025-08-30T11:14:00.000Z",
      "periodo": "2025-08",
      "producto": "TRIPAS OVINAS",
      "cantidad": 313,
      "pesoKg": 6260,
      "valorUsd": 0,
      "createdAt": "2026-07-14T15:15:03.933Z",
      "updatedAt": "2026-07-14T15:15:03.933Z",
      "productor": {
        "id": "cmrkslac50096rde8wb5mshvg",
        "nombre": "BAMIDAL S.A.",
        "cuit": null,
        "razonSocial": null,
        "pais": "Uruguay",
        "provincia": null,
        "localidad": null,
        "activo": true,
        "createdAt": "2026-07-14T15:14:39.126Z",
        "updatedAt": "2026-07-14T15:14:39.126Z"
      },
      "destino": {
        "id": "cmrksl9z90006rde8v9spkh5v",
        "nombre": "TERCEROS PAISES SÓLO A DEPÓSITOS",
        "pais": "TERCEROS PAISES SÓLO A DEPÓSITOS",
        "region": null,
        "createdAt": "2026-07-14T15:14:38.662Z",
        "updatedAt": "2026-07-14T15:14:38.662Z"
      }
    },
    {
      "id": "cmrkslss10w8lrde8gkyjo0bg",
      "productorId": "cmrkslac50096rde8wb5mshvg",
      "certificadorId": null,
      "competidorId": "cmrkslam500gdrde8tyf4qsis",
      "destinoId": "cmrksl9zf000arde84pjk649e",
      "contenedorId": null,
      "importacionId": "cmrksl9z60003rde8f5zrkgr1",
      "fecha": "2025-08-27T14:39:00.000Z",
      "periodo": "2025-08",
      "producto": "CARNE OVINA CON HUESOS EN CORTES",
      "cantidad": 207,
      "pesoKg": 3586,
      "valorUsd": 0,
      "createdAt": "2026-07-14T15:15:03.012Z",
      "updatedAt": "2026-07-14T15:15:03.012Z",
      "productor": {
        "id": "cmrkslac50096rde8wb5mshvg",
        "nombre": "BAMIDAL S.A.",
        "cuit": null,
        "razonSocial": null,
        "pais": "Uruguay",
        "provincia": null,
        "localidad": null,
        "activo": true,
        "createdAt": "2026-07-14T15:14:39.126Z",
        "updatedAt": "2026-07-14T15:14:39.126Z"
      },
      "destino": {
        "id": "cmrksl9zf000arde84pjk649e",
        "nombre": "BRASIL",
        "pais": "BRASIL",
        "region": null,
        "createdAt": "2026-07-14T15:14:38.667Z",
        "updatedAt": "2026-07-14T15:14:38.667Z"
      }
    },
    {
      "id": "cmrkslss10w8erde8dh4fezjn",
      "productorId": "cmrkslac50096rde8wb5mshvg",
      "certificadorId": null,
      "competidorId": "cmrkslam500gdrde8tyf4qsis",
      "destinoId": "cmrksl9zf000arde84pjk649e",
      "contenedorId": null,
      "importacionId": "cmrksl9z60003rde8f5zrkgr1",
      "fecha": "2025-08-27T11:08:00.000Z",
      "periodo": "2025-08",
      "producto": "CARNE OVINA CON HUESO CONGELADA",
      "cantidad": 813,
      "pesoKg": 14177,
      "valorUsd": 0,
      "createdAt": "2026-07-14T15:15:03.012Z",
      "updatedAt": "2026-07-14T15:15:03.012Z",
      "productor": {
        "id": "cmrkslac50096rde8wb5mshvg",
        "nombre": "BAMIDAL S.A.",
        "cuit": null,
        "razonSocial": null,
        "pais": "Uruguay",
        "provincia": null,
        "localidad": null,
        "activo": true,
        "createdAt": "2026-07-14T15:14:39.126Z",
        "updatedAt": "2026-07-14T15:14:39.126Z"
      },
      "destino": {
        "id": "cmrksl9zf000arde84pjk649e",
        "nombre": "BRASIL",
        "pais": "BRASIL",
        "region": null,
        "createdAt": "2026-07-14T15:14:38.667Z",
        "updatedAt": "2026-07-14T15:14:38.667Z"
      }
    },
    {
      "id": "cmrksls2h0v55rde80ie983t5",
      "productorId": "cmrkslac50096rde8wb5mshvg",
      "certificadorId": null,
      "competidorId": "cmrkslam500gdrde8tyf4qsis",
      "destinoId": "cmrksl9zf000arde84pjk649e",
      "contenedorId": null,
      "importacionId": "cmrksl9z60003rde8f5zrkgr1",
      "fecha": "2025-08-19T16:21:00.000Z",
      "periodo": "2025-08",
      "producto": "CARNE OVINA CON HUESO CONGELADA",
      "cantidad": 1170,
      "pesoKg": 20063,
      "valorUsd": 0,
      "createdAt": "2026-07-14T15:15:02.089Z",
      "updatedAt": "2026-07-14T15:15:02.089Z",
      "productor": {
        "id": "cmrkslac50096rde8wb5mshvg",
        "nombre": "BAMIDAL S.A.",
        "cuit": null,
        "razonSocial": null,
        "pais": "Uruguay",
        "provincia": null,
        "localidad": null,
        "activo": true,
        "createdAt": "2026-07-14T15:14:39.126Z",
        "updatedAt": "2026-07-14T15:14:39.126Z"
      },
      "destino": {
        "id": "cmrksl9zf000arde84pjk649e",
        "nombre": "BRASIL",
        "pais": "BRASIL",
        "region": null,
        "createdAt": "2026-07-14T15:14:38.667Z",
        "updatedAt": "2026-07-14T15:14:38.667Z"
      }
    },
    {
      "id": "cmrkslrbu0tz9rde85j10xn1k",
      "productorId": "cmrkslac50096rde8wb5mshvg",
      "certificadorId": null,
      "competidorId": "cmrkslam500gdrde8tyf4qsis",
      "destinoId": "cmrksl9zf000arde84pjk649e",
      "contenedorId": null,
      "importacionId": "cmrksl9z60003rde8f5zrkgr1",
      "fecha": "2025-08-11T11:10:59.999Z",
      "periodo": "2025-08",
      "producto": "CARNE OVINA CON HUESO CONGELADA",
      "cantidad": 1126,
      "pesoKg": 21014,
      "valorUsd": 0,
      "createdAt": "2026-07-14T15:15:01.128Z",
      "updatedAt": "2026-07-14T15:15:01.128Z",
      "productor": {
        "id": "cmrkslac50096rde8wb5mshvg",
        "nombre": "BAMIDAL S.A.",
        "cuit": null,
        "razonSocial": null,
        "pais": "Uruguay",
        "provincia": null,
        "localidad": null,
        "activo": true,
        "createdAt": "2026-07-14T15:14:39.126Z",
        "updatedAt": "2026-07-14T15:14:39.126Z"
      },
      "destino": {
        "id": "cmrksl9zf000arde84pjk649e",
        "nombre": "BRASIL",
        "pais": "BRASIL",
        "region": null,
        "createdAt": "2026-07-14T15:14:38.667Z",
        "updatedAt": "2026-07-14T15:14:38.667Z"
      }
    },
    {
      "id": "cmrkslrbj0te9rde871ehp86c",
      "productorId": "cmrkslac50096rde8wb5mshvg",
      "certificadorId": null,
      "competidorId": "cmrkslam500gdrde8tyf4qsis",
      "destinoId": "cmrksl9zf000arde84pjk649e",
      "contenedorId": null,
      "importacionId": "cmrksl9z60003rde8f5zrkgr1",
      "fecha": "2025-08-05T13:21:59.999Z",
      "periodo": "2025-08",
      "producto": "CARNE OVINA CON HUESOS EN CORTES",
      "cantidad": 95,
      "pesoKg": 1562,
      "valorUsd": 0,
      "createdAt": "2026-07-14T15:15:01.128Z",
      "updatedAt": "2026-07-14T15:15:01.128Z",
      "productor": {
        "id": "cmrkslac50096rde8wb5mshvg",
        "nombre": "BAMIDAL S.A.",
        "cuit": null,
        "razonSocial": null,
        "pais": "Uruguay",
        "provincia": null,
        "localidad": null,
        "activo": true,
        "createdAt": "2026-07-14T15:14:39.126Z",
        "updatedAt": "2026-07-14T15:14:39.126Z"
      },
      "destino": {
        "id": "cmrksl9zf000arde84pjk649e",
        "nombre": "BRASIL",
        "pais": "BRASIL",
        "region": null,
        "createdAt": "2026-07-14T15:14:38.667Z",
        "updatedAt": "2026-07-14T15:14:38.667Z"
      }
    },
    {
      "id": "cmrkslrbj0teorde89bxiarel",
      "productorId": "cmrkslac50096rde8wb5mshvg",
      "certificadorId": null,
      "competidorId": "cmrkslam500gdrde8tyf4qsis",
      "destinoId": "cmrksla5q0040rde81mdgkryj",
      "contenedorId": null,
      "importacionId": "cmrksl9z60003rde8f5zrkgr1",
      "fecha": "2025-08-05T13:21:59.999Z",
      "periodo": "2025-08",
      "producto": "SUBPRODUCTO OVINO NO COMESTIBLE",
      "cantidad": 25,
      "pesoKg": 468,
      "valorUsd": 0,
      "createdAt": "2026-07-14T15:15:01.128Z",
      "updatedAt": "2026-07-14T15:15:01.128Z",
      "productor": {
        "id": "cmrkslac50096rde8wb5mshvg",
        "nombre": "BAMIDAL S.A.",
        "cuit": null,
        "razonSocial": null,
        "pais": "Uruguay",
        "provincia": null,
        "localidad": null,
        "activo": true,
        "createdAt": "2026-07-14T15:14:39.126Z",
        "updatedAt": "2026-07-14T15:14:39.126Z"
      },
      "destino": {
        "id": "cmrksla5q0040rde81mdgkryj",
        "nombre": "UNION EUROPEA SÓLO A DEPÓSITO",
        "pais": "UNION EUROPEA SÓLO A DEPÓSITO",
        "region": null,
        "createdAt": "2026-07-14T15:14:38.894Z",
        "updatedAt": "2026-07-14T15:14:38.894Z"
      }
    },
    {
      "id": "cmrkslrbj0texrde8r557ljc0",
      "productorId": "cmrkslac50096rde8wb5mshvg",
      "certificadorId": null,
      "competidorId": "cmrkslam500gdrde8tyf4qsis",
      "destinoId": "cmrksl9z90006rde8v9spkh5v",
      "contenedorId": null,
      "importacionId": "cmrksl9z60003rde8f5zrkgr1",
      "fecha": "2025-08-05T13:21:59.999Z",
      "periodo": "2025-08",
      "producto": "CARNE OVINA SIN HUESO ENFRIADA",
      "cantidad": 3,
      "pesoKg": 45,
      "valorUsd": 0,
      "createdAt": "2026-07-14T15:15:01.128Z",
      "updatedAt": "2026-07-14T15:15:01.128Z",
      "productor": {
        "id": "cmrkslac50096rde8wb5mshvg",
        "nombre": "BAMIDAL S.A.",
        "cuit": null,
        "razonSocial": null,
        "pais": "Uruguay",
        "provincia": null,
        "localidad": null,
        "activo": true,
        "createdAt": "2026-07-14T15:14:39.126Z",
        "updatedAt": "2026-07-14T15:14:39.126Z"
      },
      "destino": {
        "id": "cmrksl9z90006rde8v9spkh5v",
        "nombre": "TERCEROS PAISES SÓLO A DEPÓSITOS",
        "pais": "TERCEROS PAISES SÓLO A DEPÓSITOS",
        "region": null,
        "createdAt": "2026-07-14T15:14:38.662Z",
        "updatedAt": "2026-07-14T15:14:38.662Z"
      }
    },
    {
      "id": "cmrkslrbi0te6rde8fa6eugf4",
      "productorId": "cmrkslac50096rde8wb5mshvg",
      "certificadorId": null,
      "competidorId": "cmrkslam500gdrde8tyf4qsis",
      "destinoId": "cmrksl9zf000arde84pjk649e",
      "contenedorId": null,
      "importacionId": "cmrksl9z60003rde8f5zrkgr1",
      "fecha": "2025-08-05T10:11:00.000Z",
      "periodo": "2025-08",
      "producto": "CARNE OVINA CON HUESO CONGELADA",
      "cantidad": 376,
      "pesoKg": 6543,
      "valorUsd": 0,
      "createdAt": "2026-07-14T15:15:01.128Z",
      "updatedAt": "2026-07-14T15:15:01.128Z",
      "productor": {
        "id": "cmrkslac50096rde8wb5mshvg",
        "nombre": "BAMIDAL S.A.",
        "cuit": null,
        "razonSocial": null,
        "pais": "Uruguay",
        "provincia": null,
        "localidad": null,
        "activo": true,
        "createdAt": "2026-07-14T15:14:39.126Z",
        "updatedAt": "2026-07-14T15:14:39.126Z"
      },
      "destino": {
        "id": "cmrksl9zf000arde84pjk649e",
        "nombre": "BRASIL",
        "pais": "BRASIL",
        "region": null,
        "createdAt": "2026-07-14T15:14:38.667Z",
        "updatedAt": "2026-07-14T15:14:38.667Z"
      }
    },
    {
      "id": "cmrkslrbj0telrde8sfpmwdo6",
      "productorId": "cmrkslac50096rde8wb5mshvg",
      "certificadorId": null,
      "competidorId": "cmrkslam500gdrde8tyf4qsis",
      "destinoId": "cmrksla5q0040rde81mdgkryj",
      "contenedorId": null,
      "importacionId": "cmrksl9z60003rde8f5zrkgr1",
      "fecha": "2025-08-05T10:11:00.000Z",
      "periodo": "2025-08",
      "producto": "SUBPRODUCTO OVINO NO COMESTIBLE",
      "cantidad": 361,
      "pesoKg": 6637,
      "valorUsd": 0,
      "createdAt": "2026-07-14T15:15:01.128Z",
      "updatedAt": "2026-07-14T15:15:01.128Z",
      "productor": {
        "id": "cmrkslac50096rde8wb5mshvg",
        "nombre": "BAMIDAL S.A.",
        "cuit": null,
        "razonSocial": null,
        "pais": "Uruguay",
        "provincia": null,
        "localidad": null,
        "activo": true,
        "createdAt": "2026-07-14T15:14:39.126Z",
        "updatedAt": "2026-07-14T15:14:39.126Z"
      },
      "destino": {
        "id": "cmrksla5q0040rde81mdgkryj",
        "nombre": "UNION EUROPEA SÓLO A DEPÓSITO",
        "pais": "UNION EUROPEA SÓLO A DEPÓSITO",
        "region": null,
        "createdAt": "2026-07-14T15:14:38.894Z",
        "updatedAt": "2026-07-14T15:14:38.894Z"
      }
    },
    {
      "id": "cmrkslrbj0terrde8yseh9ufu",
      "productorId": "cmrkslac50096rde8wb5mshvg",
      "certificadorId": null,
      "competidorId": "cmrkslam500gdrde8tyf4qsis",
      "destinoId": "cmrksl9z90006rde8v9spkh5v",
      "contenedorId": null,
      "importacionId": "cmrksl9z60003rde8f5zrkgr1",
      "fecha": "2025-08-05T10:11:00.000Z",
      "periodo": "2025-08",
      "producto": "CARNE OVINA SIN HUESO CONGELADA",
      "cantidad": 76,
      "pesoKg": 1439,
      "valorUsd": 0,
      "createdAt": "2026-07-14T15:15:01.128Z",
      "updatedAt": "2026-07-14T15:15:01.128Z",
      "productor": {
        "id": "cmrkslac50096rde8wb5mshvg",
        "nombre": "BAMIDAL S.A.",
        "cuit": null,
        "razonSocial": null,
        "pais": "Uruguay",
        "provincia": null,
        "localidad": null,
        "activo": true,
        "createdAt": "2026-07-14T15:14:39.126Z",
        "updatedAt": "2026-07-14T15:14:39.126Z"
      },
      "destino": {
        "id": "cmrksl9z90006rde8v9spkh5v",
        "nombre": "TERCEROS PAISES SÓLO A DEPÓSITOS",
        "pais": "TERCEROS PAISES SÓLO A DEPÓSITOS",
        "region": null,
        "createdAt": "2026-07-14T15:14:38.662Z",
        "updatedAt": "2026-07-14T15:14:38.662Z"
      }
    },
    {
      "id": "cmrkslpx50rorrde810uoewcg",
      "productorId": "cmrkslac50096rde8wb5mshvg",
      "certificadorId": null,
      "competidorId": "cmrkslam500gdrde8tyf4qsis",
      "destinoId": "cmrksl9zf000arde84pjk649e",
      "contenedorId": null,
      "importacionId": "cmrksl9z60003rde8f5zrkgr1",
      "fecha": "2025-07-25T13:30:59.999Z",
      "periodo": "2025-07",
      "producto": "CARNE OVINA CON HUESO CONGELADA",
      "cantidad": 1620,
      "pesoKg": 19208,
      "valorUsd": 0,
      "createdAt": "2026-07-14T15:14:59.306Z",
      "updatedAt": "2026-07-14T15:14:59.306Z",
      "productor": {
        "id": "cmrkslac50096rde8wb5mshvg",
        "nombre": "BAMIDAL S.A.",
        "cuit": null,
        "razonSocial": null,
        "pais": "Uruguay",
        "provincia": null,
        "localidad": null,
        "activo": true,
        "createdAt": "2026-07-14T15:14:39.126Z",
        "updatedAt": "2026-07-14T15:14:39.126Z"
      },
      "destino": {
        "id": "cmrksl9zf000arde84pjk649e",
        "nombre": "BRASIL",
        "pais": "BRASIL",
        "region": null,
        "createdAt": "2026-07-14T15:14:38.667Z",
        "updatedAt": "2026-07-14T15:14:38.667Z"
      }
    },
    {
      "id": "cmrkslpx50rourde8p479nyym",
      "productorId": "cmrkslac50096rde8wb5mshvg",
      "certificadorId": null,
      "competidorId": "cmrkslam500gdrde8tyf4qsis",
      "destinoId": "cmrksl9zf000arde84pjk649e",
      "contenedorId": null,
      "importacionId": "cmrksl9z60003rde8f5zrkgr1",
      "fecha": "2025-07-25T11:17:00.000Z",
      "periodo": "2025-07",
      "producto": "CARNE OVINA CON HUESOS EN CORTES",
      "cantidad": 152,
      "pesoKg": 1540,
      "valorUsd": 0,
      "createdAt": "2026-07-14T15:14:59.306Z",
      "updatedAt": "2026-07-14T15:14:59.306Z",
      "productor": {
        "id": "cmrkslac50096rde8wb5mshvg",
        "nombre": "BAMIDAL S.A.",
        "cuit": null,
        "razonSocial": null,
        "pais": "Uruguay",
        "provincia": null,
        "localidad": null,
        "activo": true,
        "createdAt": "2026-07-14T15:14:39.126Z",
        "updatedAt": "2026-07-14T15:14:39.126Z"
      },
      "destino": {
        "id": "cmrksl9zf000arde84pjk649e",
        "nombre": "BRASIL",
        "pais": "BRASIL",
        "region": null,
        "createdAt": "2026-07-14T15:14:38.667Z",
        "updatedAt": "2026-07-14T15:14:38.667Z"
      }
    },
    {
      "id": "cmrkslp4z0qjgrde8so5g9l8r",
      "productorId": "cmrkslac50096rde8wb5mshvg",
      "certificadorId": null,
      "competidorId": "cmrkslam500gdrde8tyf4qsis",
      "destinoId": "cmrksl9zf000arde84pjk649e",
      "contenedorId": null,
      "importacionId": "cmrksl9z60003rde8f5zrkgr1",
      "fecha": "2025-07-16T12:27:00.000Z",
      "periodo": "2025-07",
      "producto": "CARNE OVINA CON HUESO CONGELADA",
      "cantidad": 1239,
      "pesoKg": 20634,
      "valorUsd": 0,
      "createdAt": "2026-07-14T15:14:58.291Z",
      "updatedAt": "2026-07-14T15:14:58.291Z",
      "productor": {
        "id": "cmrkslac50096rde8wb5mshvg",
        "nombre": "BAMIDAL S.A.",
        "cuit": null,
        "razonSocial": null,
        "pais": "Uruguay",
        "provincia": null,
        "localidad": null,
        "activo": true,
        "createdAt": "2026-07-14T15:14:39.126Z",
        "updatedAt": "2026-07-14T15:14:39.126Z"
      },
      "destino": {
        "id": "cmrksl9zf000arde84pjk649e",
        "nombre": "BRASIL",
        "pais": "BRASIL",
        "region": null,
        "createdAt": "2026-07-14T15:14:38.667Z",
        "updatedAt": "2026-07-14T15:14:38.667Z"
      }
    },
    {
      "id": "cmrkslod80pcgrde87wn7njv3",
      "productorId": "cmrkslac50096rde8wb5mshvg",
      "certificadorId": null,
      "competidorId": "cmrkslam500gdrde8tyf4qsis",
      "destinoId": "cmrksl9zf000arde84pjk649e",
      "contenedorId": null,
      "importacionId": "cmrksl9z60003rde8f5zrkgr1",
      "fecha": "2025-07-07T12:06:59.999Z",
      "periodo": "2025-07",
      "producto": "CARNE OVINA CON HUESOS EN CORTES",
      "cantidad": 581,
      "pesoKg": 9162,
      "valorUsd": 0,
      "createdAt": "2026-07-14T15:14:57.292Z",
      "updatedAt": "2026-07-14T15:14:57.292Z",
      "productor": {
        "id": "cmrkslac50096rde8wb5mshvg",
        "nombre": "BAMIDAL S.A.",
        "cuit": null,
        "razonSocial": null,
        "pais": "Uruguay",
        "provincia": null,
        "localidad": null,
        "activo": true,
        "createdAt": "2026-07-14T15:14:39.126Z",
        "updatedAt": "2026-07-14T15:14:39.126Z"
      },
      "destino": {
        "id": "cmrksl9zf000arde84pjk649e",
        "nombre": "BRASIL",
        "pais": "BRASIL",
        "region": null,
        "createdAt": "2026-07-14T15:14:38.667Z",
        "updatedAt": "2026-07-14T15:14:38.667Z"
      }
    },
    {
      "id": "cmrkslod80pcyrde8p013r4h0",
      "productorId": "cmrkslac50096rde8wb5mshvg",
      "certificadorId": null,
      "competidorId": "cmrkslam500gdrde8tyf4qsis",
      "destinoId": "cmrksl9z90006rde8v9spkh5v",
      "contenedorId": null,
      "importacionId": "cmrksl9z60003rde8f5zrkgr1",
      "fecha": "2025-07-07T12:06:59.999Z",
      "periodo": "2025-07",
      "producto": "CARNE OVINA SIN HUESO ENFRIADA",
      "cantidad": 15,
      "pesoKg": 288,
      "valorUsd": 0,
      "createdAt": "2026-07-14T15:14:57.292Z",
      "updatedAt": "2026-07-14T15:14:57.292Z",
      "productor": {
        "id": "cmrkslac50096rde8wb5mshvg",
        "nombre": "BAMIDAL S.A.",
        "cuit": null,
        "razonSocial": null,
        "pais": "Uruguay",
        "provincia": null,
        "localidad": null,
        "activo": true,
        "createdAt": "2026-07-14T15:14:39.126Z",
        "updatedAt": "2026-07-14T15:14:39.126Z"
      },
      "destino": {
        "id": "cmrksl9z90006rde8v9spkh5v",
        "nombre": "TERCEROS PAISES SÓLO A DEPÓSITOS",
        "pais": "TERCEROS PAISES SÓLO A DEPÓSITOS",
        "region": null,
        "createdAt": "2026-07-14T15:14:38.662Z",
        "updatedAt": "2026-07-14T15:14:38.662Z"
      }
    },
    {
      "id": "cmrkslod80pc9rde80cacu90t",
      "productorId": "cmrkslac50096rde8wb5mshvg",
      "certificadorId": null,
      "competidorId": "cmrkslam500gdrde8tyf4qsis",
      "destinoId": "cmrksl9zf000arde84pjk649e",
      "contenedorId": null,
      "importacionId": "cmrksl9z60003rde8f5zrkgr1",
      "fecha": "2025-07-07T08:50:00.000Z",
      "periodo": "2025-07",
      "producto": "CARNE OVINA CON HUESO CONGELADA",
      "cantidad": 659,
      "pesoKg": 10813,
      "valorUsd": 0,
      "createdAt": "2026-07-14T15:14:57.292Z",
      "updatedAt": "2026-07-14T15:14:57.292Z",
      "productor": {
        "id": "cmrkslac50096rde8wb5mshvg",
        "nombre": "BAMIDAL S.A.",
        "cuit": null,
        "razonSocial": null,
        "pais": "Uruguay",
        "provincia": null,
        "localidad": null,
        "activo": true,
        "createdAt": "2026-07-14T15:14:39.126Z",
        "updatedAt": "2026-07-14T15:14:39.126Z"
      },
      "destino": {
        "id": "cmrksl9zf000arde84pjk649e",
        "nombre": "BRASIL",
        "pais": "BRASIL",
        "region": null,
        "createdAt": "2026-07-14T15:14:38.667Z",
        "updatedAt": "2026-07-14T15:14:38.667Z"
      }
    },
    {
      "id": "cmrkslod00ovhrde8sbk2al14",
      "productorId": "cmrkslac50096rde8wb5mshvg",
      "certificadorId": null,
      "competidorId": "cmrkslam500gdrde8tyf4qsis",
      "destinoId": "cmrksl9zf000arde84pjk649e",
      "contenedorId": null,
      "importacionId": "cmrksl9z60003rde8f5zrkgr1",
      "fecha": "2025-07-03T10:52:00.000Z",
      "periodo": "2025-07",
      "producto": "CARNE OVINA CON HUESO CONGELADA",
      "cantidad": 1918,
      "pesoKg": 20800,
      "valorUsd": 0,
      "createdAt": "2026-07-14T15:14:57.292Z",
      "updatedAt": "2026-07-14T15:14:57.292Z",
      "productor": {
        "id": "cmrkslac50096rde8wb5mshvg",
        "nombre": "BAMIDAL S.A.",
        "cuit": null,
        "razonSocial": null,
        "pais": "Uruguay",
        "provincia": null,
        "localidad": null,
        "activo": true,
        "createdAt": "2026-07-14T15:14:39.126Z",
        "updatedAt": "2026-07-14T15:14:39.126Z"
      },
      "destino": {
        "id": "cmrksl9zf000arde84pjk649e",
        "nombre": "BRASIL",
        "pais": "BRASIL",
        "region": null,
        "createdAt": "2026-07-14T15:14:38.667Z",
        "updatedAt": "2026-07-14T15:14:38.667Z"
      }
    },
    {
      "id": "cmrkslocy0orlrde8b6fubbjs",
      "productorId": "cmrkslac50096rde8wb5mshvg",
      "certificadorId": null,
      "competidorId": "cmrkslam500gdrde8tyf4qsis",
      "destinoId": "cmrksl9zf000arde84pjk649e",
      "contenedorId": null,
      "importacionId": "cmrksl9z60003rde8f5zrkgr1",
      "fecha": "2025-06-30T11:42:00.000Z",
      "periodo": "2025-06",
      "producto": "CARNE OVINA CON HUESO CONGELADA",
      "cantidad": 1032,
      "pesoKg": 16079,
      "valorUsd": 0,
      "createdAt": "2026-07-14T15:14:57.292Z",
      "updatedAt": "2026-07-14T15:14:57.292Z",
      "productor": {
        "id": "cmrkslac50096rde8wb5mshvg",
        "nombre": "BAMIDAL S.A.",
        "cuit": null,
        "razonSocial": null,
        "pais": "Uruguay",
        "provincia": null,
        "localidad": null,
        "activo": true,
        "createdAt": "2026-07-14T15:14:39.126Z",
        "updatedAt": "2026-07-14T15:14:39.126Z"
      },
      "destino": {
        "id": "cmrksl9zf000arde84pjk649e",
        "nombre": "BRASIL",
        "pais": "BRASIL",
        "region": null,
        "createdAt": "2026-07-14T15:14:38.667Z",
        "updatedAt": "2026-07-14T15:14:38.667Z"
      }
    },
    {
      "id": "cmrkslocz0oscrde8auplne35",
      "productorId": "cmrkslac50096rde8wb5mshvg",
      "certificadorId": null,
      "competidorId": "cmrkslam500gdrde8tyf4qsis",
      "destinoId": "cmrksl9z90006rde8v9spkh5v",
      "contenedorId": null,
      "importacionId": "cmrksl9z60003rde8f5zrkgr1",
      "fecha": "2025-06-30T11:42:00.000Z",
      "periodo": "2025-06",
      "producto": "CARNE OVINA SIN HUESO CONGELADA",
      "cantidad": 71,
      "pesoKg": 1373,
      "valorUsd": 0,
      "createdAt": "2026-07-14T15:14:57.292Z",
      "updatedAt": "2026-07-14T15:14:57.292Z",
      "productor": {
        "id": "cmrkslac50096rde8wb5mshvg",
        "nombre": "BAMIDAL S.A.",
        "cuit": null,
        "razonSocial": null,
        "pais": "Uruguay",
        "provincia": null,
        "localidad": null,
        "activo": true,
        "createdAt": "2026-07-14T15:14:39.126Z",
        "updatedAt": "2026-07-14T15:14:39.126Z"
      },
      "destino": {
        "id": "cmrksl9z90006rde8v9spkh5v",
        "nombre": "TERCEROS PAISES SÓLO A DEPÓSITOS",
        "pais": "TERCEROS PAISES SÓLO A DEPÓSITOS",
        "region": null,
        "createdAt": "2026-07-14T15:14:38.662Z",
        "updatedAt": "2026-07-14T15:14:38.662Z"
      }
    },
    {
      "id": "cmrkslod20p0brde8iydlvtor",
      "productorId": "cmrkslac50096rde8wb5mshvg",
      "certificadorId": null,
      "competidorId": "cmrkslam500gdrde8tyf4qsis",
      "destinoId": "cmrksla5q0040rde81mdgkryj",
      "contenedorId": null,
      "importacionId": "cmrksl9z60003rde8f5zrkgr1",
      "fecha": "2025-06-30T11:42:00.000Z",
      "periodo": "2025-06",
      "producto": "SUBPRODUCTO OVINO NO COMESTIBLE",
      "cantidad": 164,
      "pesoKg": 3115,
      "valorUsd": 0,
      "createdAt": "2026-07-14T15:14:57.292Z",
      "updatedAt": "2026-07-14T15:14:57.292Z",
      "productor": {
        "id": "cmrkslac50096rde8wb5mshvg",
        "nombre": "BAMIDAL S.A.",
        "cuit": null,
        "razonSocial": null,
        "pais": "Uruguay",
        "provincia": null,
        "localidad": null,
        "activo": true,
        "createdAt": "2026-07-14T15:14:39.126Z",
        "updatedAt": "2026-07-14T15:14:39.126Z"
      },
      "destino": {
        "id": "cmrksla5q0040rde81mdgkryj",
        "nombre": "UNION EUROPEA SÓLO A DEPÓSITO",
        "pais": "UNION EUROPEA SÓLO A DEPÓSITO",
        "region": null,
        "createdAt": "2026-07-14T15:14:38.894Z",
        "updatedAt": "2026-07-14T15:14:38.894Z"
      }
    }
  ],
  "clientes": [],
  "captaciones": [],
  "evolucion": [
    {
      "periodo": "2025-01",
      "operaciones": 52,
      "peso": 200618,
      "clientes": 1
    },
    {
      "periodo": "2025-02",
      "operaciones": 11,
      "peso": 46643,
      "clientes": 1
    },
    {
      "periodo": "2025-03",
      "operaciones": 1,
      "peso": 1302,
      "clientes": 1
    },
    {
      "periodo": "2025-04",
      "operaciones": 0,
      "peso": 0,
      "clientes": 0
    },
    {
      "periodo": "2025-05",
      "operaciones": 0,
      "peso": 0,
      "clientes": 0
    },
    {
      "periodo": "2025-06",
      "operaciones": 4,
      "peso": 39741,
      "clientes": 1
    },
    {
      "periodo": "2025-07",
      "operaciones": 7,
      "peso": 82445,
      "clientes": 1
    },
    {
      "periodo": "2025-08",
      "operaciones": 11,
      "peso": 81794,
      "clientes": 1
    },
    {
      "periodo": "2025-09",
      "operaciones": 15,
      "peso": 69094,
      "clientes": 1
    },
    {
      "periodo": "2025-10",
      "operaciones": 0,
      "peso": 0,
      "clientes": 0
    },
    {
      "periodo": "2025-11",
      "operaciones": 13,
      "peso": 92718,
      "clientes": 1
    },
    {
      "periodo": "2025-12",
      "operaciones": 1,
      "peso": 18816,
      "clientes": 1
    },
    {
      "periodo": "2026-01",
      "operaciones": 0,
      "peso": 0,
      "clientes": 0
    },
    {
      "periodo": "2026-02",
      "operaciones": 0,
      "peso": 0,
      "clientes": 0
    },
    {
      "periodo": "2026-03",
      "operaciones": 0,
      "peso": 0,
      "clientes": 0
    },
    {
      "periodo": "2026-04",
      "operaciones": 0,
      "peso": 0,
      "clientes": 0
    },
    {
      "periodo": "2026-05",
      "operaciones": 0,
      "peso": 0,
      "clientes": 0
    },
    {
      "periodo": "2026-06",
      "operaciones": 0,
      "peso": 0,
      "clientes": 0
    },
    {
      "periodo": "2026-07",
      "operaciones": 0,
      "peso": 0,
      "clientes": 0
    }
  ],
  "compartidos": [],
  "exclusivos": [],
  "totalClientes": 0,
  "totalCompartidos": 0,
  "totalExclusivos": 0
}